aic_tools_alpaca/__init__.py
aic_tools_alpaca/account_info.py
aic_tools_alpaca-1.0.1.dist-info/METADATA
aic_tools_alpaca-1.0.1.dist-info/WHEEL
aic_tools_alpaca-1.0.1.dist-info/top_level.txt
aic_tools_alpaca-1.0.1.dist-info/RECORD
