Metadata-Version: 2.1
Name: aic_tools_alpaca
Version: 1.0.1
Summary: Alpaca tools for AI Characters
Author: Viacheslav Kovalevskyi
Author-email: viacheslav@kovalevskyi.com
License: MIT
Requires-Dist: alpaca-py ==0.21.0
Requires-Dist: crewai-tools ==0.2.3
